rustc_dev_t_x64_win_msvc_nightly_p2/__init__.py
rustc_dev_t_x64_win_msvc_nightly_p2/data/icu_provider_macros-d4f887cd84c98d98.dll
rustc_dev_t_x64_win_msvc_nightly_p2/data/libanstyle-558d1d49cde9e529.rmeta
rustc_dev_t_x64_win_msvc_nightly_p2/data/libdatafrog-5eebbbc482d64e15.rmeta
rustc_dev_t_x64_win_msvc_nightly_p2/data/libdigest-0b8e8a9b324f193c.rmeta
rustc_dev_t_x64_win_msvc_nightly_p2/data/libfallible_iterator-ab4f8070d1666a25.rmeta
rustc_dev_t_x64_win_msvc_nightly_p2/data/libintl_memoizer-ae393222bb8b1f97.rmeta
rustc_dev_t_x64_win_msvc_nightly_p2/data/liblock_api-bbc625c6addf524d.rmeta
rustc_dev_t_x64_win_msvc_nightly_p2/data/libmatchers-787d80314ee63d2d.rmeta
rustc_dev_t_x64_win_msvc_nightly_p2/data/libobject-385a2f7eb46e72d0.rmeta
rustc_dev_t_x64_win_msvc_nightly_p2/data/libobject-687e2cf0ae664305.rmeta
rustc_dev_t_x64_win_msvc_nightly_p2/data/librand_xoshiro-a63948d5cd59fdf9.rmeta
rustc_dev_t_x64_win_msvc_nightly_p2/data/librustc_ast_passes-f9fb1ea3f6972018.rmeta
rustc_dev_t_x64_win_msvc_nightly_p2/data/librustc_borrowck-b96456f9468d1321.rmeta
rustc_dev_t_x64_win_msvc_nightly_p2/data/librustc_error_messages-52fd6219b711556c.rmeta
rustc_dev_t_x64_win_msvc_nightly_p2/data/librustc_expand-3206f762a0ee3890.rmeta
rustc_dev_t_x64_win_msvc_nightly_p2/data/librustc_metadata-20702300767ad3d7.rmeta
rustc_dev_t_x64_win_msvc_nightly_p2/data/librustc_public_bridge-0dc9f75e2b353cc8.rlib
rustc_dev_t_x64_win_msvc_nightly_p2/data/librustc_sanitizers-874e1933b32d42db.rmeta
rustc_dev_t_x64_win_msvc_nightly_p2/data/libshlex-dab5d4b1f6100089.rmeta
rustc_dev_t_x64_win_msvc_nightly_p2/data/libtempfile-6031b220b955787a.rmeta
rustc_dev_t_x64_win_msvc_nightly_p2/data/libtracing_core-2147d38fd76968e2.rmeta
rustc_dev_t_x64_win_msvc_nightly_p2/data/libwindows_core-5506c93c865fef3c.rmeta
rustc_dev_t_x64_win_msvc_nightly_p2/data/proc_macro_hack-60c8d6ce2b0435a6.dll.lib
rustc_dev_t_x64_win_msvc_nightly_p2/data/rustc_driver-00a065e462aa96d9.pdb
rustc_dev_t_x64_win_msvc_nightly_p2-1.91.0.dist-info/METADATA
rustc_dev_t_x64_win_msvc_nightly_p2-1.91.0.dist-info/WHEEL
rustc_dev_t_x64_win_msvc_nightly_p2-1.91.0.dist-info/top_level.txt
rustc_dev_t_x64_win_msvc_nightly_p2-1.91.0.dist-info/RECORD
